ch_method/__init__.py
ch_method/constants.py
ch_method/core.py
ch_method/helpers.py
ch_method-0.1.0.dist-info/METADATA
ch_method-0.1.0.dist-info/WHEEL
ch_method-0.1.0.dist-info/top_level.txt
ch_method-0.1.0.dist-info/RECORD
